{
"meta":{"test_sets":[],"test_metrics":[],"learn_metrics":[{"best_value":"Min","name":"Logloss"}],"launch_mode":"Train","parameters":"","iteration_count":100,"learn_sets":["learn"],"name":"experiment"},
"iterations":[
{"learn":[0.6839543426],"iteration":0,"passed_time":0.01165141306,"remaining_time":1.153489893},
{"learn":[0.6719750328],"iteration":1,"passed_time":0.01712077753,"remaining_time":0.8389180988},
{"learn":[0.6608966903],"iteration":2,"passed_time":0.02133285963,"remaining_time":0.6897624614},
{"learn":[0.651523968],"iteration":3,"passed_time":0.02718900377,"remaining_time":0.6525360904},
{"learn":[0.6476481562],"iteration":4,"passed_time":0.03243029961,"remaining_time":0.6161756926},
{"learn":[0.643868021],"iteration":5,"passed_time":0.04187417772,"remaining_time":0.6560287843},
{"learn":[0.6402235339],"iteration":6,"passed_time":0.04988966138,"remaining_time":0.6628197869},
{"learn":[0.637257983],"iteration":7,"passed_time":0.05546015663,"remaining_time":0.6377918012},
{"learn":[0.6342484797],"iteration":8,"passed_time":0.06410476208,"remaining_time":0.6481703722},
{"learn":[0.6315277424],"iteration":9,"passed_time":0.07275831239,"remaining_time":0.6548248115},
{"learn":[0.6288959744],"iteration":10,"passed_time":0.08364449971,"remaining_time":0.6767600431},
{"learn":[0.6250133479],"iteration":11,"passed_time":0.1215935017,"remaining_time":0.8916856792},
{"learn":[0.6239397001],"iteration":12,"passed_time":0.1290051031,"remaining_time":0.863341844},
{"learn":[0.6234729257],"iteration":13,"passed_time":0.1334419414,"remaining_time":0.819714783},
{"learn":[0.6220363645],"iteration":14,"passed_time":0.1375910796,"remaining_time":0.7796827843},
{"learn":[0.6216650612],"iteration":15,"passed_time":0.1462494061,"remaining_time":0.7678093818},
{"learn":[0.621044053],"iteration":16,"passed_time":0.1506231167,"remaining_time":0.7353952166},
{"learn":[0.6202532347],"iteration":17,"passed_time":0.158316387,"remaining_time":0.7212190966},
{"learn":[0.619562788],"iteration":18,"passed_time":0.1651188201,"remaining_time":0.7039276014},
{"learn":[0.616595087],"iteration":19,"passed_time":0.1692877342,"remaining_time":0.6771509367},
{"learn":[0.615946226],"iteration":20,"passed_time":0.1764601122,"remaining_time":0.6638261363},
{"learn":[0.6152025236],"iteration":21,"passed_time":0.1808164343,"remaining_time":0.641076449},
{"learn":[0.6140591276],"iteration":22,"passed_time":0.1854266984,"remaining_time":0.6207763381},
{"learn":[0.6106926172],"iteration":23,"passed_time":0.1916486388,"remaining_time":0.6068873563},
{"learn":[0.6101181744],"iteration":24,"passed_time":0.2031987799,"remaining_time":0.6095963396},
{"learn":[0.6091172922],"iteration":25,"passed_time":0.2229105946,"remaining_time":0.634437846},
{"learn":[0.6087083162],"iteration":26,"passed_time":0.2484261105,"remaining_time":0.6716705952},
{"learn":[0.6081052892],"iteration":27,"passed_time":0.2624370647,"remaining_time":0.6748381664},
{"learn":[0.6077087949],"iteration":28,"passed_time":0.2675473028,"remaining_time":0.6550296034},
{"learn":[0.6071584063],"iteration":29,"passed_time":0.2768666593,"remaining_time":0.646022205},
{"learn":[0.6054526691],"iteration":30,"passed_time":0.2829376385,"remaining_time":0.6297644212},
{"learn":[0.6052100593],"iteration":31,"passed_time":0.2919952819,"remaining_time":0.6204899741},
{"learn":[0.6047494548],"iteration":32,"passed_time":0.2984659219,"remaining_time":0.6059762656},
{"learn":[0.6044042851],"iteration":33,"passed_time":0.306808735,"remaining_time":0.5955698973},
{"learn":[0.6042036164],"iteration":34,"passed_time":0.3120713842,"remaining_time":0.5795611421},
{"learn":[0.6038297198],"iteration":35,"passed_time":0.3171561102,"remaining_time":0.5638330848},
{"learn":[0.6014514227],"iteration":36,"passed_time":0.3243961458,"remaining_time":0.5523501942},
{"learn":[0.6009932466],"iteration":37,"passed_time":0.3296865996,"remaining_time":0.5379097151},
{"learn":[0.6007876756],"iteration":38,"passed_time":0.3350048616,"remaining_time":0.523981963},
{"learn":[0.6004876105],"iteration":39,"passed_time":0.3409220697,"remaining_time":0.5113831045},
{"learn":[0.6001198851],"iteration":40,"passed_time":0.3458478009,"remaining_time":0.4976834208},
{"learn":[0.599498788],"iteration":41,"passed_time":0.3501831034,"remaining_time":0.4835861904},
{"learn":[0.5991395735],"iteration":42,"passed_time":0.3601196419,"remaining_time":0.4773678974},
{"learn":[0.5973782509],"iteration":43,"passed_time":0.3670424841,"remaining_time":0.4671449798},
{"learn":[0.5965109022],"iteration":44,"passed_time":0.3743943641,"remaining_time":0.4575931117},
{"learn":[0.5961224802],"iteration":45,"passed_time":0.3789815511,"remaining_time":0.444891386},
{"learn":[0.5957904604],"iteration":46,"passed_time":0.3839216495,"remaining_time":0.4329329239},
{"learn":[0.5941897973],"iteration":47,"passed_time":0.3913276185,"remaining_time":0.4239382534},
{"learn":[0.5937522372],"iteration":48,"passed_time":0.3956228255,"remaining_time":0.4117706959},
{"learn":[0.5935421235],"iteration":49,"passed_time":0.399912035,"remaining_time":0.399912035},
{"learn":[0.5927508989],"iteration":50,"passed_time":0.4066565366,"remaining_time":0.3907092214},
{"learn":[0.5923517753],"iteration":51,"passed_time":0.4111534176,"remaining_time":0.3795262316},
{"learn":[0.591712092],"iteration":52,"passed_time":0.4156229303,"remaining_time":0.3685712778},
{"learn":[0.5913195425],"iteration":53,"passed_time":0.4201897539,"remaining_time":0.3579394199},
{"learn":[0.5908291758],"iteration":54,"passed_time":0.4246675702,"remaining_time":0.3474552847},
{"learn":[0.5892773274],"iteration":55,"passed_time":0.4300802431,"remaining_time":0.337920191},
{"learn":[0.5890676721],"iteration":56,"passed_time":0.4393783237,"remaining_time":0.3314608407},
{"learn":[0.5888556053],"iteration":57,"passed_time":0.4533006231,"remaining_time":0.3282521754},
{"learn":[0.5885250836],"iteration":58,"passed_time":0.4582302093,"remaining_time":0.3184311624},
{"learn":[0.5882524805],"iteration":59,"passed_time":0.4621853208,"remaining_time":0.3081235472},
{"learn":[0.5878018452],"iteration":60,"passed_time":0.4666777268,"remaining_time":0.298367727},
{"learn":[0.5873711497],"iteration":61,"passed_time":0.471900493,"remaining_time":0.2892293344},
{"learn":[0.5868737265],"iteration":62,"passed_time":0.4769909939,"remaining_time":0.2801375679},
{"learn":[0.5863519241],"iteration":63,"passed_time":0.4818372015,"remaining_time":0.2710334258},
{"learn":[0.5859109094],"iteration":64,"passed_time":0.4916091878,"remaining_time":0.2647126396},
{"learn":[0.5854736486],"iteration":65,"passed_time":0.4996604083,"remaining_time":0.2574008164},
{"learn":[0.5850994154],"iteration":66,"passed_time":0.5083862436,"remaining_time":0.2503991946},
{"learn":[0.5850229346],"iteration":67,"passed_time":0.5162753082,"remaining_time":0.2429530862},
{"learn":[0.5846594375],"iteration":68,"passed_time":0.524563256,"remaining_time":0.2356733469},
{"learn":[0.5845668833],"iteration":69,"passed_time":0.5375610861,"remaining_time":0.2303833226},
{"learn":[0.5837836723],"iteration":70,"passed_time":0.5455963907,"remaining_time":0.22284923},
{"learn":[0.583631218],"iteration":71,"passed_time":0.5577439428,"remaining_time":0.2169004222},
{"learn":[0.5833066889],"iteration":72,"passed_time":0.5659318898,"remaining_time":0.2093172743},
{"learn":[0.5815397877],"iteration":73,"passed_time":0.5750706631,"remaining_time":0.2020518546},
{"learn":[0.5811947441],"iteration":74,"passed_time":0.581412424,"remaining_time":0.1938041413},
{"learn":[0.58038453],"iteration":75,"passed_time":0.6362861331,"remaining_time":0.2009324631},
{"learn":[0.5802646559],"iteration":76,"passed_time":0.6514567838,"remaining_time":0.1945909874},
{"learn":[0.579054859],"iteration":77,"passed_time":0.66821497,"remaining_time":0.188470889},
{"learn":[0.5778609539],"iteration":78,"passed_time":0.6854836537,"remaining_time":0.1822171738},
{"learn":[0.5773628611],"iteration":79,"passed_time":0.695371533,"remaining_time":0.1738428833},
{"learn":[0.5770179161],"iteration":80,"passed_time":0.70840726,"remaining_time":0.1661696042},
{"learn":[0.5767926528],"iteration":81,"passed_time":0.7132534514,"remaining_time":0.1565678308},
{"learn":[0.576177188],"iteration":82,"passed_time":0.7181627091,"remaining_time":0.1470935669},
{"learn":[0.5760544521],"iteration":83,"passed_time":0.723208027,"remaining_time":0.1377539099},
{"learn":[0.5757114861],"iteration":84,"passed_time":0.7270822899,"remaining_time":0.1283086394},
{"learn":[0.5751269327],"iteration":85,"passed_time":0.7346700808,"remaining_time":0.119597455},
{"learn":[0.5746991703],"iteration":86,"passed_time":0.7385869392,"remaining_time":0.1103635656},
{"learn":[0.5740539536],"iteration":87,"passed_time":0.7432658908,"remaining_time":0.1013544397},
{"learn":[0.5738296471],"iteration":88,"passed_time":0.7476892169,"remaining_time":0.0924110268},
{"learn":[0.5731284775],"iteration":89,"passed_time":0.7528157597,"remaining_time":0.08364619552},
{"learn":[0.5725158858],"iteration":90,"passed_time":0.7560275688,"remaining_time":0.07477195735},
{"learn":[0.5721130857],"iteration":91,"passed_time":0.7629309376,"remaining_time":0.06634182066},
{"learn":[0.5719888105],"iteration":92,"passed_time":0.7667560125,"remaining_time":0.05771281815},
{"learn":[0.5710825899],"iteration":93,"passed_time":0.7690368037,"remaining_time":0.04908745556},
{"learn":[0.5708148774],"iteration":94,"passed_time":0.7716038463,"remaining_time":0.04061072875},
{"learn":[0.5701610077],"iteration":95,"passed_time":0.7739738723,"remaining_time":0.03224891134},
{"learn":[0.5699035314],"iteration":96,"passed_time":0.7767688972,"remaining_time":0.02402378033},
{"learn":[0.5698261053],"iteration":97,"passed_time":0.7806907493,"remaining_time":0.01593246427},
{"learn":[0.5692801579],"iteration":98,"passed_time":0.7860957986,"remaining_time":0.007940361602},
{"learn":[0.568876443],"iteration":99,"passed_time":0.7917997428,"remaining_time":0}
]}